agentspeak/__init__.py
agentspeak/__main__.py
agentspeak/ext_stdlib.py
agentspeak/lexer.py
agentspeak/optimizer.py
agentspeak/parser.py
agentspeak/runtime.py
agentspeak/stdlib.py
agentspeak/util.py
agentspeak-0.2.2.dist-info/AUTHORS.rst
agentspeak-0.2.2.dist-info/LICENSE.txt
agentspeak-0.2.2.dist-info/METADATA
agentspeak-0.2.2.dist-info/WHEEL
agentspeak-0.2.2.dist-info/top_level.txt
agentspeak-0.2.2.dist-info/RECORD
