Metadata-Version: 2.1
Name: agentspeak
Version: 0.2.2
Summary: JASON-style AgentSpeak for Python.
Home-page: https://github.com/niklasf/python-agentspeak
Author: Niklas Fiekas
Author-email: niklas.fiekas@tu-clausthal.de
License: GPL3
Keywords: jason multi agent simulation agent-speak
Classifier: Development Status :: 3 - Alpha
Classifier: Environment :: Console
Classifier: Intended Audience :: Developers
Classifier: Intended Audience :: Science/Research
Classifier: License :: OSI Approved :: GNU General Public License v3 (GPLv3)
Classifier: Operating System :: OS Independent
Classifier: Programming Language :: Python
Classifier: Programming Language :: Python :: 2
Classifier: Programming Language :: Python :: 2.7
Classifier: Programming Language :: Python :: 3
Classifier: Programming Language :: Python :: 3.3
Classifier: Programming Language :: Python :: 3.4
Classifier: Programming Language :: Python :: 3.5
Classifier: Programming Language :: Python :: 3.6
Classifier: Programming Language :: Python :: 3.7
Classifier: Programming Language :: Python :: 3.8
Classifier: Programming Language :: Python :: 3.9
Classifier: Programming Language :: Python :: 3.10
Classifier: Programming Language :: Python :: 3.11
Classifier: Programming Language :: Other
Classifier: Topic :: Scientific/Engineering
Classifier: Topic :: Scientific/Engineering :: Artificial Intelligence
Classifier: Topic :: Software Development
Classifier: Topic :: Software Development :: Interpreters
Classifier: Topic :: Software Development :: Libraries
License-File: LICENSE.txt
License-File: AUTHORS.rst
Requires-Dist: colorama
